seaflow/__init__.py
seaflow/hooks/__init__.py
seaflow/hooks/hook.py
seaflow/ios/__init__.py
seaflow/ios/io.py
seaflow/nodes/__init__.py
seaflow/nodes/node.py
seaflow/runners/__init__.py
seaflow/runners/dagrunner.py
seaflow/runners/sequencerunner.py
seaflow/schedulers/__init__.py
seaflow/schedulers/dag.py
seaflow/schedulers/pipeline.py
seaflow/test/test_dager.py
seaflow/test/test_dagrunner_function.py
seaflow/test/test_dagrunner_node.py
seaflow/test/test_pipeline.py
shihua_seaflow-0.1.1.dist-info/METADATA
shihua_seaflow-0.1.1.dist-info/WHEEL
shihua_seaflow-0.1.1.dist-info/top_level.txt
shihua_seaflow-0.1.1.dist-info/RECORD
